chart_genius_mcp/__init__.py
chart_genius_mcp/__main__.py
chart_genius_mcp/cli.py
chart_genius_mcp/config.py
chart_genius_mcp/exceptions.py
chart_genius_mcp/http_server.py
chart_genius_mcp/schemas.py
chart_genius_mcp/server.py
chart_genius_mcp/types.py
chart_genius_mcp/ai/__init__.py
chart_genius_mcp/ai/chart_detector.py
chart_genius_mcp/ai/insight_generator.py
chart_genius_mcp/ai/providers.py
chart_genius_mcp/core/data_optimizer.py
chart_genius_mcp/core/performance.py
chart_genius_mcp/engines/__init__.py
chart_genius_mcp/engines/matplotlib_engine.py
chart_genius_mcp/engines/plotly_engine.py
chart_genius_mcp/engines/seaborn_engine.py
chart_genius_mcp/optimization/__init__.py
chart_genius_mcp/optimization/algorithms.py
chart_genius_mcp/optimization/caching.py
chart_genius_mcp-1.0.2.dist-info/METADATA
chart_genius_mcp-1.0.2.dist-info/WHEEL
chart_genius_mcp-1.0.2.dist-info/entry_points.txt
chart_genius_mcp-1.0.2.dist-info/licenses/LICENSE
chart_genius_mcp-1.0.2.dist-info/RECORD
